{
    "grado": "enfermeria",
    "materia": "pae",
    "bloque": 9,
    "nombre": "Proceso de Atención (PAE) Nivel 9",
    "meses": "Evaluación Clínica 9",
    "temas": [
        "Fisiopatología",
        "Normatividad",
        "Casos Clínicos"
    ],
    "totalEjercicios": 8,
    "ejercicios": {
        "v1": [
            {
                "id": "enf_pae_9_1",
                "tipo": "selección",
                "vineta": "",
                "pregunta": "¿Signo clínico universal temprano de la hipoxia cerebral?",
                "opciones": [
                    "Bradicardia profunda",
                    "Alteración del estado de alerta (Ansiedad)",
                    "Fiebre",
                    "Cianosis central"
                ],
                "respuestaCorrecta": "Alteración del estado de alerta (Ansiedad)",
                "retroalimentacion": "Antes de ponerse azul (cianosis) que es un evento súmamente tardío, la neurona exige oxígeno disparando ansiedad brutal, agresividad y confusión en el paciente."
            },
            {
                "id": "enf_pae_9_2",
                "tipo": "selección",
                "vineta": "",
                "pregunta": "Frecuencia de compresiones torácicas en RCP AHA:",
                "opciones": [
                    "160 / min",
                    "140 / min",
                    "100 a 120 / min",
                    "80 a 100 / min"
                ],
                "respuestaCorrecta": "100 a 120 / min",
                "retroalimentacion": "Más rápido que eso no deja que el corazón se llene de sangre antes de la siguiente compresión. Más bajo que eso no genera perfusión coronaria mínima (15 mmHg)."
            },
            {
                "id": "enf_pae_9_3",
                "tipo": "selección",
                "vineta": "",
                "pregunta": "¿Vía de administración con biodisponibilidad del 100% inmediata?",
                "opciones": [
                    "Intramuscular",
                    "Oral",
                    "Intravenosa",
                    "Sublingual"
                ],
                "respuestaCorrecta": "Intravenosa",
                "retroalimentacion": "Al entrar directo al torrente sanguíneo central, evita el efecto de primer paso hepático por completo."
            }
        ],
        "v2": []
    }
}